{
  "kind": "singleType",
  "collectionName": "home_medias",
  "info": {
    "singularName": "home-media",
    "pluralName": "home-medias",
    "displayName": "Home_media",
    "description": ""
  },
  "options": {
    "draftAndPublish": true
  },
  "pluginOptions": {},
  "attributes": {
    "Cover_image": {
      "type": "media",
      "multiple": false,
      "required": true,
      "allowedTypes": [
        "images"
      ]
    },
    "Project_logo": {
      "type": "media",
      "multiple": false,
      "required": true,
      "allowedTypes": [
        "images"
      ]
    },
    "Section_divider": {
      "type": "media",
      "multiple": false,
      "required": true,
      "allowedTypes": [
        "images"
      ]
    },
    "Team_image": {
      "type": "media",
      "multiple": false,
      "required": true,
      "allowedTypes": [
        "images"
      ]
    },
    "Mission_text": {
      "type": "text",
      "required": true
    }
  }
}
